{
  "$shared": {
    "X-Version": "1.0"
  },
    "docker": {
      "Unsafe_HostAddress": "https://localhost:7104",
      "Safe_HostAddress" : "Http://localhost:5265"
    },
    "dev": {
      "Unsafe_HostAddress": "https://localhost:7104",
      "Safe_HostAddress" : "Http://localhost:5265"
    },
    "stage": {
      "Unsafe_HostAddress": "https://localhost:7104",
      "Safe_HostAddress" : "Http://localhost:5265"
    },
    "prod": {
      "Unsafe_HostAddress": "https://localhost:7104",
      "Safe_HostAddress" : "Http://localhost:5265"
    }
  }